{
  "sources": {
    "Manual Submission": 4,
    "BBC": 3414,
    "Sky": 2231,
    "Telegraph": 832,
    "Manual": 4,
    "BBC News US": 668,
    "Sky News US": 154,
    "BBC-UK": 2,
    "BBC-Politics": 2,
    "BBC-Business": 2
  },
  "categories": {
    "Politics": 4348,
    "Crime & Legal": 1548,
    "Notable International": 39,
    "Economy": 131,
    "Sport": 289,
    "Royals": 284,
    "Immigration": 8,
    "Breaking News": 384,
    "Culture": 43,
    "Environment": 139,
    "Entertainment": 41,
    "Sports": 56,
    "Notable International News\ud83c\udf0d": 3
  }
}