{
  "sources": {
    "Manual Submission": 4,
    "BBC": 3319,
    "Sky": 2206,
    "Telegraph": 817,
    "Manual": 4,
    "BBC News US": 630,
    "Sky News US": 147,
    "BBC-UK": 2,
    "BBC-Politics": 2,
    "BBC-Business": 2
  },
  "categories": {
    "Politics": 4298,
    "Crime & Legal": 1497,
    "Notable International": 39,
    "Economy": 123,
    "Sport": 270,
    "Royals": 279,
    "Immigration": 3,
    "Breaking News": 357,
    "Culture": 41,
    "Environment": 139,
    "Entertainment": 41,
    "Sports": 43,
    "Notable International News\ud83c\udf0d": 3
  }
}